updownserver/__init__.py
updownserver/__main__.py
updownserver/cgi.py
updownserver-1.0.3.dist-info/licenses/LICENSE
updownserver-1.0.3.dist-info/METADATA
updownserver-1.0.3.dist-info/WHEEL
updownserver-1.0.3.dist-info/entry_points.txt
updownserver-1.0.3.dist-info/top_level.txt
updownserver-1.0.3.dist-info/RECORD
