Metadata-Version: 2.4
Name: updownserver
Version: 1.0.3
Summary: A lightweight HTTP server with unified upload/download interface
Home-page: https://github.com/harry18456/updownserver
Author: Harry (Original by Densaugeo)
Author-email: harry18456@gmail.com
Classifier: Programming Language :: Python :: 3
Classifier: License :: OSI Approved :: MIT License
Classifier: Operating System :: OS Independent
Requires-Python: >=3.9
License-File: LICENSE
Provides-Extra: qr
Requires-Dist: qrcode; extra == "qr"
Dynamic: author
Dynamic: author-email
Dynamic: classifier
Dynamic: description
Dynamic: description-content-type
Dynamic: home-page
Dynamic: license-file
Dynamic: provides-extra
Dynamic: requires-python
Dynamic: summary
